visilens/LensModelMCMC.py
visilens/__init__.py
visilens/calc_likelihood.py
visilens/class_utils.py
visilens/lensing.py
visilens/plot_images.py
visilens/triangleplot.py
visilens/utils.py
visilens-0.1.dist-info/LICENSE.txt
visilens-0.1.dist-info/METADATA
visilens-0.1.dist-info/WHEEL
visilens-0.1.dist-info/top_level.txt
visilens-0.1.dist-info/RECORD
